{
	"AT2021ahip":{
		"schema":"https://github.com/astrocatalogs/supernovae/blob/d3ef5fc/SCHEMA.md",
		"name":"AT2021ahip",
		"sources":[
			{
				"name":"Pan-STARRS 3Pi",
				"url":"https://www.wis-tns.org/object/2021ahip",
				"alias":"1"
			},
			{
				"name":"Latest Supernovae",
				"secondary":true,
				"url":"http://www.rochesterastronomy.org/snimages/snredshiftall.html",
				"alias":"2"
			},
			{
				"name":"The Open Supernova Catalog",
				"bibcode":"2017ApJ...835...64G",
				"reference":"Guillochon et al. (2017)",
				"secondary":true,
				"url":"https://sne.space",
				"alias":"3"
			}
		],
		"alias":[
			{
				"value":"AT2021ahip",
				"source":"1,2"
			},
			{
				"value":"PS21ods",
				"source":"1,2"
			}
		],
		"claimedtype":[
			{
				"value":"Candidate",
				"source":"3"
			}
		],
		"dec":[
			{
				"value":"+06:01:33.58",
				"u_value":"degrees",
				"source":"1,2"
			}
		],
		"discoverdate":[
			{
				"value":"2021/10/30",
				"source":"1,2"
			}
		],
		"discoverer":[
			{
				"value":"PS1",
				"source":"1,2"
			}
		],
		"maxappmag":[
			{
				"value":"21",
				"derived":true,
				"source":"1,2,3"
			}
		],
		"maxdate":[
			{
				"value":"2021/10/29",
				"derived":true,
				"source":"1,2,3"
			}
		],
		"maxvisualappmag":[
			{
				"value":"21",
				"derived":true,
				"source":"1,2,3"
			}
		],
		"maxvisualdate":[
			{
				"value":"2021/10/29",
				"derived":true,
				"source":"1,2,3"
			}
		],
		"ra":[
			{
				"value":"21:37:53.161",
				"u_value":"hours",
				"source":"1,2"
			}
		],
		"photometry":[
			{
				"time":"59516.5",
				"magnitude":"21.0",
				"u_time":"MJD",
				"source":"1,2"
			}
		]
	}
}